Metadata-Version: 2.1
Name: compare3
Version: 1.0.4
Summary: Alternative syntax for comparing/asserting expressions in Python 3.
Home-page: https://github.com/astromness/compare
Author: Austin Stromness
Author-email: stromnessdevelopment@gmail.com
License: Simplified BSD
Download-URL: https://github.com/astromness/compare/archive/refs/tags/1.0.4.tar.gz
Keywords: python,compare,matcher,to be,to equal,assert,test equality,specification,BDD,TDD
Platform: UNKNOWN
Classifier: Development Status :: 5 - Production/Stable
Classifier: Intended Audience :: Developers
Classifier: License :: OSI Approved :: BSD License
Classifier: Programming Language :: Python :: 3
Classifier: Programming Language :: Python :: 3.9
